MANIFEST.in
README.md
README.rst
requirements.txt
setup.cfg
setup.py
app/__init__.py
app/__main__.py
app/main.py
app/src/__init__.py
app/src/arguments.py
app/src/compose_builder.py
app/src/rancher_compose.py
app/src/yml_reader.py
matador_deploy.egg-info/PKG-INFO
matador_deploy.egg-info/SOURCES.txt
matador_deploy.egg-info/dependency_links.txt
matador_deploy.egg-info/entry_points.txt
matador_deploy.egg-info/requires.txt
matador_deploy.egg-info/top_level.txt