Metadata-Version: 1.1
Name: matador-deploy
Version: 0.0.4
Summary: A Bullish Rancher Deployment CLI App
Home-page: https://github.com/seedtech/matador-deploy
Author: Timon Sotiropoulos
Author-email: timon@seeddigital.co
License: MIT
Download-URL: https://github.com/seedtech/matador-deploy/archive/0.4.tar.gz
Keywords: cli
Platform: UNKNOWN
Classifier: Intended Audience :: Developers
Classifier: Topic :: Utilities
Classifier: License :: Public Domain
Classifier: Natural Language :: English
Classifier: Operating System :: OS Independent
Classifier: Programming Language :: Python :: 2
Classifier: Programming Language :: Python :: 2.6
Classifier: Programming Language :: Python :: 2.7
Classifier: Programming Language :: Python :: 3
Classifier: Programming Language :: Python :: 3.2
Classifier: Programming Language :: Python :: 3.3
Classifier: Programming Language :: Python :: 3.4
